karrio/mappers/hermes/__init__.py
karrio/mappers/hermes/mapper.py
karrio/mappers/hermes/proxy.py
karrio/mappers/hermes/settings.py
karrio/plugins/hermes/__init__.py
karrio/providers/hermes/__init__.py
karrio/providers/hermes/error.py
karrio/providers/hermes/tracking.py
karrio/providers/hermes/units.py
karrio/providers/hermes/utils.py
karrio/providers/hermes/pickup/__init__.py
karrio/providers/hermes/pickup/cancel.py
karrio/providers/hermes/pickup/create.py
karrio/providers/hermes/shipment/__init__.py
karrio/providers/hermes/shipment/create.py
karrio/schemas/hermes/__init__.py
karrio/schemas/hermes/error_response.py
karrio/schemas/hermes/pickup_cancel_request.py
karrio/schemas/hermes/pickup_cancel_response.py
karrio/schemas/hermes/pickup_create_request.py
karrio/schemas/hermes/pickup_create_response.py
karrio/schemas/hermes/shipment_request.py
karrio/schemas/hermes/shipment_response.py
karrio/schemas/hermes/tracking_response.py
karrio_hermes-2026.1.4.dist-info/METADATA
karrio_hermes-2026.1.4.dist-info/WHEEL
karrio_hermes-2026.1.4.dist-info/entry_points.txt
karrio_hermes-2026.1.4.dist-info/top_level.txt
karrio_hermes-2026.1.4.dist-info/RECORD
